{
  "meta": {
    "name": "light",
    "description": "Light theme for profile card"
  },
  "blocks": {
    "app": {
      "background": "#edf1f5",
      "card_surface": "#e6ebf2",
      "text_primary": "#1f2937",
      "ascii_art_text": "#000000",
      "ascii_auto_invert": "true",
      "ascii_inner_background": "#edf1f6cc",
      "text_muted": "#5b6473",
      "decorative_flag": "#e48a67",
      "decorative_accent_secondary": "#d97757",
      "decorative_edge_highlight": "#efb39a",
      "card_outline_stroke": "#c8d2e0",
      "info_strip_background": "#d7dde6"
    },
    "code_window": {
      "background": "#f8fafc",
      "border": "#d6deea",
      "header_background": "#f1f5f9",
      "text_primary": "#1f2937",
      "text_muted": "#6b7280",
      "traffic_dot_1": "#ff5f56",
      "traffic_dot_2": "#f7c28a",
      "traffic_dot_3": "#f3b179",
      "terminal_background": "#eef3f8",
      "terminal_border": "#ccd6e4",
      "terminal_prompt": "#d97745",
      "terminal_text": "#334155",
      "terminal_cursor": "#334155"
    },
    "quotes_window": {
      "panel_background": "#f8fafc",
      "panel_stroke": "#d3dce9",
      "header_background": "#f8f0eb",
      "tab_background": "#f5ece6",
      "tab_stroke": "#e5d2c6",
      "tab_text": "#334155",
      "status_text": "#64748b",
      "gutter_background": "#f6efea",
      "gutter_stroke": "#d6deea",
      "line_number_text": "#8f8177",
      "scramble_text": "#d66e52",
      "quote_text": "#1f2937",
      "title_text": "#d97706"
    },
    "status_window": {
      "panel_background": "#f7f9fc",
      "panel_stroke": "#d3dce9",
      "header_background": "#faeee8",
      "header_accent": "#e07a55",
      "header_bubble_background": "#f8cfbb",
      "header_bubble_stroke": "#eca98a",
      "header_bubble_text": "#8b4635",
      "header_title_text": "#334155",
      "close_button_stroke": "#64748b",
      "close_button_text": "#64748b",
      "markdown_text": "#273444",
      "markdown_error_text": "#b91c1c"
    },
    "about_markup": {
      "default_text": "#334155",
      "header": "#0f172a",
      "dim": "#8a94a680",
      "label": "#e7a66f",
      "value": "#ff5f56"
    }
  }
}
